dreamongym/__init__.py
dreamongym/e01.py
dream_on_gym-0.0.1.dist-info/COPYING.md
dream_on_gym-0.0.1.dist-info/METADATA
dream_on_gym-0.0.1.dist-info/WHEEL
dream_on_gym-0.0.1.dist-info/top_level.txt
dream_on_gym-0.0.1.dist-info/RECORD
