Metadata-Version: 2.1
Name: dream-on-gym
Version: 0.0.1
Home-page: https://gitlab.com/IRO-Team/dream-on-gym
Author: Hermann Ignacio Pempelfort Vergara
Author-email: hermann.pempelfort@usm.cl
License-File: COPYING.md
Requires-Dist: numpy
Requires-Dist: jsonschema
Requires-Dist: gym (==0.21.0)
Requires-Dist: importlib-metadata (==4.13.0)
Requires-Dist: tensorflow (==1.15.0)
Requires-Dist: tensorflow-gpu (==1.15)
Requires-Dist: protobuf (==3.20.0)
Requires-Dist: stable-baselines[mpi]
Requires-Dist: stable-baselines3[extra]
Requires-Dist: mpi4py
